monkey_vision/__init__.py
monkey_vision/__main__.py
monkey_vision/vision.py
monkey_vision/app/__init__.py
monkey_vision/app/vision_compare.py
monkey_vision/app/vision_points.py
monkey_vision/app/vision_text.py
monkey_vision/app/vision_ui.py
monkey_vision/app/math/__init__.py
monkey_vision/app/math/data_sorting.py
monkey_vision/app/math/union_find.py
monkey_vision/app/math/utils.py
monkey_vision/app/utils/__init__.py
monkey_vision/app/utils/data_utils.py
monkey_vision/app/utils/group_points.py
monkey_vision/app/utils/image_utils.py
monkey_vision/app/utils/string_utils.py
monkey_vision/app/utils/text_utils.py
monkey_vision/app/vision/__init__.py
monkey_vision/app/vision/contours_utils.py
monkey_vision/app/vision/edges.py
monkey_vision/app/vision/image_matching.py
monkey_vision/app/vision/image_processing.py
monkey_vision-0.1.2.dist-info/METADATA
monkey_vision-0.1.2.dist-info/WHEEL
monkey_vision-0.1.2.dist-info/top_level.txt
monkey_vision-0.1.2.dist-info/RECORD
