Metadata-Version: 2.1
Name: monkey-vision
Version: 0.1.2
Summary: Computer vision image analyses for monkey screenshots.
Home-page: https://github.com/monkey-cli/monkey_vision
Author: Valdio Veliu <Valdio Veliu>
Author-email: valdioveliu@gmail.com
License: UNKNOWN
Platform: UNKNOWN
Requires-Python: >=3.6
Requires-Dist: numpy (>=1.18.0)
Requires-Dist: opencv-python (>=4.4.0)
Requires-Dist: pytesseract (==0.3.6)
Provides-Extra: dev
Requires-Dist: pre-commit (==2.7.1) ; extra == 'dev'
Requires-Dist: matplotlib (==3.3.1) ; extra == 'dev'
